{
  "parent": "block/block",
  "textures": {
    "casing": "create:block/brass_casing",
    "panel": "minecraft:block/deepslate_tiles",
    "coil": "minecraft:block/copper_block",
    "screen": "minecraft:block/lime_concrete",
    "particle": "create:block/brass_casing"
  },
  "elements": [
    {
      "from": [
        0,
        0,
        0
      ],
      "to": [
        16,
        3,
        16
      ],
      "faces": {
        "north": {
          "texture": "#casing"
        },
        "south": {
          "texture": "#casing"
        },
        "east": {
          "texture": "#casing"
        },
        "west": {
          "texture": "#casing"
        },
        "up": {
          "texture": "#casing"
        },
        "down": {
          "texture": "#casing"
        }
      }
    },
    {
      "from": [
        2,
        3,
        2
      ],
      "to": [
        14,
        5,
        14
      ],
      "faces": {
        "north": {
          "texture": "#panel"
        },
        "south": {
          "texture": "#panel"
        },
        "east": {
          "texture": "#panel"
        },
        "west": {
          "texture": "#panel"
        },
        "up": {
          "texture": "#panel"
        }
      }
    },
    {
      "from": [
        5,
        5,
        5
      ],
      "to": [
        11,
        8,
        11
      ],
      "faces": {
        "north": {
          "texture": "#coil"
        },
        "south": {
          "texture": "#coil"
        },
        "east": {
          "texture": "#coil"
        },
        "west": {
          "texture": "#coil"
        },
        "up": {
          "texture": "#coil"
        }
      }
    },
    {
      "from": [
        3,
        8,
        0
      ],
      "to": [
        13,
        14,
        1
      ],
      "faces": {
        "north": {
          "texture": "#screen"
        }
      }
    }
  ],
  "display": {
    "gui": {
      "rotation": [
        30,
        225,
        0
      ],
      "scale": [
        0.55,
        0.55,
        0.55
      ]
    }
  }
}
